proxychains_conf_generator/__init__.py
proxychains_conf_generator/proxychains_conf_generator.py
proxychains_conf_generator-2.0.3.dist-info/LICENSE
proxychains_conf_generator-2.0.3.dist-info/METADATA
proxychains_conf_generator-2.0.3.dist-info/WHEEL
proxychains_conf_generator-2.0.3.dist-info/top_level.txt
proxychains_conf_generator-2.0.3.dist-info/RECORD
